Metadata-Version: 2.1
Name: python-env-OTC2025
Version: 1.7
Summary: Helper for installing the Python environment for the OTC 2025 interactive lectures based on SEAScope
Home-page: https://pypi.org/project/python-env-OTC2025/
Author: Sylvain Herlédan
Author-email: sylvain.herledan@oceandatalab.com
Project-URL: Homepage, https://oceantrainingcourse2025.esa.int/
Project-URL: Issues, https://forum.oceandatalab.com/seascope
License-File: COPYING
License-File: COPYING.LESSER
Requires-Dist: pySEAScope[processor]
Requires-Dist: idf-converter
Requires-Dist: gputil
Requires-Dist: scipy
Requires-Dist: matplotlib
Requires-Dist: numba
Requires-Dist: pywinpty; sys_platform == "win32"
Requires-Dist: jupyterlab
Requires-Dist: xarray
Requires-Dist: dask[array,diagnostics,distributed]
Requires-Dist: pooch
Requires-Dist: fluxengine
Requires-Dist: bokeh
Requires-Dist: cartopy
Requires-Dist: cmocean
Requires-Dist: distributed
Requires-Dist: hda
Requires-Dist: ipywidgets
Requires-Dist: netCDF4
Requires-Dist: eumdac
Requires-Dist: scikit-image
Requires-Dist: shapely
Requires-Dist: beautifulsoup4
Requires-Dist: cdsapi
Requires-Dist: ephem
Requires-Dist: pandas
Requires-Dist: urllib3
Requires-Dist: copernicusmarine
